README.rst
setup.py
SpatialGlue_3M/SpatialGlue_pyG.py
SpatialGlue_3M/main.py
SpatialGlue_3M/model.py
SpatialGlue_3M/preprocess.py
SpatialGlue_3M/utils.py
SpatialGlue_3M.egg-info/PKG-INFO
SpatialGlue_3M.egg-info/SOURCES.txt
SpatialGlue_3M.egg-info/dependency_links.txt
SpatialGlue_3M.egg-info/not-zip-safe
SpatialGlue_3M.egg-info/requires.txt
SpatialGlue_3M.egg-info/top_level.txt