Metadata-Version: 2.1
Name: SpatialGlue-3M
Version: 0.0.2
Summary: Deciphering spatial domains from spatial multi-omics with SpatialGlue
Home-page: https://github.com/JinmiaoChenLab/SpatialGlue_3M
Author: Yahui Long
Author-email: longyh@immunol.a-star.edu.sg
License: MIT
